Metadata-Version: 1.0
Name: carter-probability
Version: 0.1
Summary: Gaussian and Binomial distributions
Home-page: UNKNOWN
Author: Carter Lam
Author-email: carterlamtlc@gmail.com
License: UNKNOWN
Platform: UNKNOWN
